conda/meta.yaml
docs/_config.yml
docs/_toc.yml
docs/index.md
docs/logo-bold.png
docs/logo.png
docs/api/config.md
docs/api/expressions.ipynb
docs/api/io.md
docs/api/rfuncs.md
docs/api/tidystats.md
docs/api/models/glm.md
docs/api/models/glmer.md
docs/api/models/index.md
docs/api/models/lm.md
docs/api/models/lmer.md
docs/api/models/skmer.md
docs/development/contributing.md
docs/development/design.md
docs/development/extending.ipynb
docs/pages/comingfromR.md
docs/pages/faqs.ipynb
docs/pages/installation.md
docs/pages/migrating.md
docs/pages/new.md
docs/pages/quickstart.ipynb
docs/tutorials/01_lm.ipynb
docs/tutorials/02_categorical.ipynb
docs/tutorials/03_lmms.ipynb
docs/tutorials/04_glmms.ipynb
docs/tutorials/nn_mediation.ipynb
pymer4/__init__.py
pymer4/config.py
pymer4/expressions.py
pymer4/io.py
pymer4/rfuncs.py
pymer4/version.py
pymer4/models/__init__.py
pymer4/models/base.py
pymer4/models/glm.py
pymer4/models/glmer.py
pymer4/models/lm.py
pymer4/models/lmer.py
pymer4/models/skmer.py
pymer4/resources/advertising.csv
pymer4/resources/chickweight.csv
pymer4/resources/credit.csv
pymer4/resources/gammas.csv
pymer4/resources/mtcars.csv
pymer4/resources/penguins.csv
pymer4/resources/poker.csv
pymer4/resources/sample_data.csv
pymer4/resources/sleep.csv
pymer4/resources/titanic.csv
pymer4/resources/titanic_test.csv
pymer4/resources/titanic_train.csv
pymer4/tests/conftest.py
pymer4/tests/test_funcs.py
pymer4/tests/test_glm.py
pymer4/tests/test_glmer.py
pymer4/tests/test_io.py
pymer4/tests/test_lm.py
pymer4/tests/test_lmer.py
pymer4/tests/test_sklearn.py
pymer4/tidystats/__init__.py
pymer4/tidystats/base.py
pymer4/tidystats/bridge.py
pymer4/tidystats/broom.py
pymer4/tidystats/easystats.py
pymer4/tidystats/emmeans_lib.py
pymer4/tidystats/lmerTest.py
pymer4/tidystats/multimodel.py
pymer4/tidystats/plutils.py
pymer4/tidystats/stats.py
pymer4/tidystats/tables.py
pymer4/tidystats/tibble.py
pymer4-0.9.2.dist-info/licenses/LICENSE.txt
pymer4-0.9.2.dist-info/METADATA
pymer4-0.9.2.dist-info/WHEEL
pymer4-0.9.2.dist-info/top_level.txt
pymer4-0.9.2.dist-info/RECORD
