Metadata-Version: 2.4
Name: pymer4
Version: 0.9.2
Summary: pymer4: all the convenience of lme4 in python
Author-email: Eshin Jolly <eshin.jolly@gmail.com>
License: MIT
Project-URL: Homepage, http://eshinjolly.com/pymer4/
Keywords: statistics,multi-level-modeling,regression,analysis
Classifier: Programming Language :: Python :: 3.10
Classifier: Programming Language :: Python :: 3.11
Classifier: Programming Language :: Python :: 3.12
Classifier: Operating System :: OS Independent
Classifier: Intended Audience :: Science/Research
Classifier: License :: OSI Approved :: MIT License
Requires-Python: >=3.10
License-File: LICENSE.txt
Dynamic: license-file
